gifconverter_hsj/__init__.py
gifconverter_hsj/converter.py
gifconverter_hsj-1.0.0.dist-info/LICENSE
gifconverter_hsj-1.0.0.dist-info/METADATA
gifconverter_hsj-1.0.0.dist-info/WHEEL
gifconverter_hsj-1.0.0.dist-info/top_level.txt
gifconverter_hsj-1.0.0.dist-info/RECORD
